
<annotation>
    <folder>French fries</folder>
    <filename>e44e37e218931885.jpg</filename>
    <path>/path/to/the/file/e44e37e218931885.jpg</path>
    <source>
        <database>Unknown</database>
    </source>
    <size>
        <width>1024</width>
        <height>564</height>
        <depth>3</depth>
    </size>
    <segmented>0</segmented>
    <object>
        <name>French fries</name>
        <pose>Unspecified</pose>
        <truncated>0</truncated>
        <difficult>0</difficult>
        <bndbox>
            <xmin>762</xmin>
            <ymin>409</ymin>
            <xmax>940</xmax>
            <ymax>498</ymax>
        </bndbox>
</object>

</annotation>
